{"cameraMode":{"drawMode":0,"name":"Shaded","section":"Shading Mode"},"sceneLighting":true,"audioPlay":false,"sceneViewState":{"m_AlwaysRefresh":false,"showFog":true,"showSkybox":true,"showFlares":true,"showImageEffects":true,"showParticleSystems":true,"showVisualEffectGraphs":true,"m_FxEnabled":true},"in2DMode":false,"pivot":{"x":-65.0931167602539,"y":-36.6785774230957,"z":55.70523452758789},"rotation":{"x":0.19705908000469209,"y":-0.46932879090309145,"z":0.10831579566001892,"w":0.853952944278717},"size":58.74119567871094,"orthographic":false}